commandex/__init__.py
commandex/commander.py
commandex/commandpack.py
commandex/executors.py
commandex/factories.py
commandex/filters.py
commandex/makers.py
commandex/parsers.py
commandex-0.3.1.dist-info/licenses/LICENSE
commandex-0.3.1.dist-info/METADATA
commandex-0.3.1.dist-info/WHEEL
commandex-0.3.1.dist-info/top_level.txt
commandex-0.3.1.dist-info/RECORD
