Metadata-Version: 2.4
Name: commandex
Version: 0.3.1
Summary: A cross-platform library for creation, storage, management of commands and command packages. Execution of commands, parsing of files with command packages.
Home-page: https://github.com/smartlegionlab/commandex/
Author: A.A. Suvorov
Author-email: smartlegiondev@gmail.com
License: BSD 3-Clause License
Project-URL: Documentation, https://github.com/smartlegionlab/commandex/blob/master/README.md
Project-URL: Release notes, https://github.com/smartlegionlab/commandex/releases
Keywords: commandex,smartlegionlab,commandman,command executor
Classifier: Development Status :: 5 - Production/Stable
Classifier: License :: OSI Approved :: BSD License
Classifier: Natural Language :: English
Classifier: Operating System :: OS Independent
Classifier: Operating System :: Microsoft :: Windows
Classifier: Operating System :: POSIX :: Linux
Classifier: Programming Language :: Python :: 3 :: Only
Classifier: Topic :: Software Development :: Libraries :: Python Modules
Requires-Python: >=3.6
License-File: LICENSE
Dynamic: license-file
